[
  { "id": 1, "name": "Arnold Press" },
  { "id": 2, "name": "Bench Press (Barbell)" },
  { "id": 3, "name": "Bench Press (Dumbbell)" },
  { "id": 4, "name": "Bench Press (Close-Grip)" },
  { "id": 5, "name": "Glute-Bridge" },
  { "id": 6, "name": "Butterfly Machine" },
  { "id": 7, "name": "Calf Raise (Seated)" },
  { "id": 8, "name": "Calf Raise (Standing)" },
  { "id": 9, "name": "Clean and Jerk" },
  { "id": 10, "name": "Crossover (Cable)" },
  { "id": 11, "name": "Crunch" },
  { "id": 12, "name": "Crunch (Exercise Ball)" },
  { "id": 13, "name": "Crunch (Kneeling, Cable)" },
  { "id": 14, "name": "Curl (Barbell)" },
  { "id": 15, "name": "Curl (Concentration)" },
  { "id": 16, "name": "Curl (Dumbbell)" },
  { "id": 17, "name": "Curl (EZ-Bar)" },
  { "id": 18, "name": "Curl (Hammer, Dumbbell)" },
  { "id": 19, "name": "Curl (Preacher)" },
  { "id": 20, "name": "Deadlift (Barbell)" },
  { "id": 21, "name": "Deadlift (Conventional)" },
  { "id": 22, "name": "Deadlift (Dumbbell)" },
  { "id": 23, "name": "Deadlift (Romanian)" },
  { "id": 24, "name": "Deadlift (Sumo)" },
  { "id": 25, "name": "Dip (Triceps)" },
  { "id": 26, "name": "Farmer's Walk" },
  { "id": 27, "name": "Fly (Chest, Machine)" },
  { "id": 28, "name": "Fly (Incline, Dumbbell)" },
  { "id": 29, "name": "Fly (Rear Delt, Cable)" },
  { "id": 30, "name": "Fly (Rear Delt, Dumbbell)" },
  { "id": 31, "name": "Front Raise (Dumbbell)" },
  { "id": 32, "name": "Goblet Squat" },
  { "id": 33, "name": "Hack Squat (Machine)" },
  { "id": 34, "name": "Lateral Raise (Cable)" },
  { "id": 35, "name": "Lateral Raise (Dumbbell)" },
  { "id": 36, "name": "Leg Extension (Machine)" },
  { "id": 37, "name": "Leg Press (Machine)" },
  { "id": 38, "name": "Leg Raise (Hanging)" },
  { "id": 39, "name": "Leg Raise (Vertical)" },
  { "id": 40, "name": "Legcurls (Lying)" },
  { "id": 41, "name": "Legcurl (Seated)" },
  { "id": 42, "name": "Lunges (Barbell)" },
  { "id": 43, "name": "Lunges (Dumbbell)" },
  { "id": 44, "name": "Mountain Climbers" },
  { "id": 45, "name": "Overhead Press (Barbell)" },
  { "id": 46, "name": "Overhead Press (Dumbbell)" },
  { "id": 47, "name": "Face-Pulls (Cable)" },
  { "id": 48, "name": "Pull-Up (Assisted)" },
  { "id": 49, "name": "Pull-Up (Weighted)" },
  { "id": 50, "name": "Push-Up (Decline)" },
  { "id": 51, "name": "Push-Up (Incline)" },
  { "id": 52, "name": "Push-Up (Weighted)" },
  { "id": 53, "name": "Row (Bent-Over)" },
  { "id": 54, "name": "Row (Cable)" },
  { "id": 55, "name": "Row (Seated Cable)" },
  { "id": 56, "name": "Row (T-Bar)" },
  { "id": 57, "name": "Row (Upright, Barbell)" },
  { "id": 58, "name": "Row (Upright, Dumbbell)" },
  { "id": 59, "name": "Russian Twist" },
  { "id": 60, "name": "Sissy Squat" },
  { "id": 61, "name": "Skull Crusher" },
  { "id": 62, "name": "Sled Push" },
  { "id": 63, "name": "Split Squat" },
  { "id": 64, "name": "Squat (Back)" },
  { "id": 65, "name": "Squat (Bodyweight)" },
  { "id": 66, "name": "Squat (Goblet)" },
  { "id": 67, "name": "Squat (Front)" },
  { "id": 68, "name": "Squat (Pistol)" },
  { "id": 69, "name": "Thrust (Hip)" },
  { "id": 70, "name": "Twist (Russian)" },
  { "id": 71, "name": "Wall Sit" },
  { "id": 72, "name": "Y-Raise (Dumbbell or Cable)" },
  { "id": 73, "name": "Pull Down (Single-Arm)" },
  { "id": 74, "name": "Pull Down (Wide-Grip)" },
  { "id": 75, "name": "Pull Down (Close-Grip)" },
  { "id": 76, "name": "Pull Down (Neutral-Grip)" },
  { "id": 77, "name": "Pull Down (Behind-the-Neck)" },
  { "id": 78, "name": "Pull Down (Straight Arm)" },
  { "id": 79, "name": "Pull Down (Reverse)" },
  { "id": 80, "name": "Pull Down (Dual Cable)" },
  { "id": 81, "name": "Hip thrust (Barbell)" },
  { "id": 82, "name": "Hip thrust (Machine)" },
  { "id": 83, "name": "Adduction (Machine)" },
  { "id": 84, "name": "Abduction (Machine)" },
  { "id": 85, "name": "Kick backs" },
  { "id": 86, "name": "Bulgarian Split Squat" },
  { "id": 87, "name": "Clean" },
  { "id": 88, "name": "Deadlift (Clean)" },
  { "id": 89, "name": "Triceps Push Down" }
]
